[{"id":1,"name":"Meredithe","retailers":["value4"],"hub_id":5},
{"id":2,"name":"Daniela","retailers":["value5"],"hub_id":3},
{"id":3,"name":"Isobel","retailers":["value1"],"hub_id":5},
{"id":4,"name":"Erny","retailers":["value3"],"hub_id":3},
{"id":5,"name":"Marta","retailers":["value4"],"hub_id":5},
{"id":6,"name":"Elisabet","retailers":["value1"],"hub_id":3},
{"id":7,"name":"Caldwell","retailers":["value3"],"hub_id":5},
{"id":8,"name":"King","retailers":["value3"],"hub_id":3},
{"id":9,"name":"Moe","retailers":["value4"],"hub_id":5},
{"id":10,"name":"Eveline","retailers":["value4"],"hub_id":3},
{"id":11,"name":"Murielle","retailers":["value4"],"hub_id":3},
{"id":12,"name":"Rasla","retailers":["value2"],"hub_id":4},
{"id":13,"name":"Ninetta","retailers":["value4"],"hub_id":5},
{"id":14,"name":"Georgeanna","retailers":["value1"],"hub_id":4},
{"id":15,"name":"Virginie","retailers":["value2"],"hub_id":3},
{"id":16,"name":"Willyt","retailers":["value3"],"hub_id":4},
{"id":17,"name":"Johnathan","retailers":["value3"],"hub_id":4},
{"id":18,"name":"Ford","retailers":["value5"],"hub_id":4},
{"id":19,"name":"Renee","retailers":["value4"],"hub_id":3},
{"id":20,"name":"Rianon","retailers":["value5"],"hub_id":4},
{"id":21,"name":"Frederic","retailers":["value5"],"hub_id":4},
{"id":22,"name":"Rosemaria","retailers":["value4"],"hub_id":3},
{"id":23,"name":"Saidee","retailers":["value3"],"hub_id":5},
{"id":24,"name":"Zena","retailers":["value1"],"hub_id":3},
{"id":25,"name":"Theresina","retailers":["value5"],"hub_id":3},
{"id":26,"name":"Alejandrina","retailers":["value2"],"hub_id":5},
{"id":27,"name":"Sterne","retailers":["value3"],"hub_id":3},
{"id":28,"name":"Allyn","retailers":["value5"],"hub_id":4},
{"id":29,"name":"Dillon","retailers":["value4"],"hub_id":3},
{"id":30,"name":"Patricio","retailers":["value5"],"hub_id":5},
{"id":31,"name":"Lewiss","retailers":["value5"],"hub_id":5},
{"id":32,"name":"Ivett","retailers":["value3"],"hub_id":5},
{"id":33,"name":"Lemuel","retailers":["value4"],"hub_id":3},
{"id":34,"name":"Fredric","retailers":["value4"],"hub_id":3},
{"id":35,"name":"Anthea","retailers":["value2"],"hub_id":5},
{"id":36,"name":"Wilow","retailers":["value2"],"hub_id":4},
{"id":37,"name":"Christel","retailers":["value5"],"hub_id":3},
{"id":38,"name":"Nicol","retailers":["value5"],"hub_id":3},
{"id":39,"name":"Chloris","retailers":["value2"],"hub_id":5},
{"id":40,"name":"Kerianne","retailers":["value4"],"hub_id":3},
{"id":41,"name":"Honey","retailers":["value2"],"hub_id":5},
{"id":42,"name":"Eydie","retailers":["value5"],"hub_id":3},
{"id":43,"name":"Antony","retailers":["value2"],"hub_id":3},
{"id":44,"name":"Judi","retailers":["value3"],"hub_id":4},
{"id":45,"name":"Worthy","retailers":["value3"],"hub_id":3},
{"id":46,"name":"Vania","retailers":["value3"],"hub_id":4},
{"id":47,"name":"Gayla","retailers":["value5"],"hub_id":5},
{"id":48,"name":"Danyelle","retailers":["value5"],"hub_id":4},
{"id":49,"name":"Mickie","retailers":["value3"],"hub_id":3},
{"id":50,"name":"Rozalin","retailers":["value4"],"hub_id":5},
{"id":51,"name":"Ly","retailers":["value2"],"hub_id":5},
{"id":52,"name":"Gaspar","retailers":["value2"],"hub_id":5},
{"id":53,"name":"Munroe","retailers":["value1"],"hub_id":3},
{"id":54,"name":"Julia","retailers":["value4"],"hub_id":3},
{"id":55,"name":"Pandora","retailers":["value1"],"hub_id":5},
{"id":56,"name":"Celinda","retailers":["value1"],"hub_id":3},
{"id":57,"name":"Almeda","retailers":["value1"],"hub_id":4},
{"id":58,"name":"Siouxie","retailers":["value2"],"hub_id":3},
{"id":59,"name":"Romonda","retailers":["value3"],"hub_id":5},
{"id":60,"name":"Carrol","retailers":["value1"],"hub_id":5},
{"id":61,"name":"Johanna","retailers":["value3"],"hub_id":5},
{"id":62,"name":"Elmore","retailers":["value2"],"hub_id":3},
{"id":63,"name":"Grier","retailers":["value1"],"hub_id":5},
{"id":64,"name":"Ardys","retailers":["value2"],"hub_id":5},
{"id":65,"name":"Moises","retailers":["value5"],"hub_id":5},
{"id":66,"name":"Dar","retailers":["value3"],"hub_id":4},
{"id":67,"name":"Anita","retailers":["value5"],"hub_id":3},
{"id":68,"name":"Pamela","retailers":["value5"],"hub_id":5},
{"id":69,"name":"Mariya","retailers":["value3"],"hub_id":4},
{"id":70,"name":"Barty","retailers":["value3"],"hub_id":3},
{"id":71,"name":"Savina","retailers":["value3"],"hub_id":4},
{"id":72,"name":"Hally","retailers":["value2"],"hub_id":5},
{"id":73,"name":"Verina","retailers":["value4"],"hub_id":5},
{"id":74,"name":"Carey","retailers":["value2"],"hub_id":5},
{"id":75,"name":"Noe","retailers":["value2"],"hub_id":5},
{"id":76,"name":"Gipsy","retailers":["value3"],"hub_id":5},
{"id":77,"name":"Geralda","retailers":["value2"],"hub_id":3},
{"id":78,"name":"Alonzo","retailers":["value1"],"hub_id":5},
{"id":79,"name":"Alvy","retailers":["value1"],"hub_id":3},
{"id":80,"name":"Jerad","retailers":["value5"],"hub_id":5},
{"id":81,"name":"Kally","retailers":["value4"],"hub_id":4},
{"id":82,"name":"Tades","retailers":["value4"],"hub_id":4},
{"id":83,"name":"Kennedy","retailers":["value2"],"hub_id":4},
{"id":84,"name":"Murdock","retailers":["value1"],"hub_id":3},
{"id":85,"name":"Josepha","retailers":["value3"],"hub_id":5},
{"id":86,"name":"Terrijo","retailers":["value3"],"hub_id":3},
{"id":87,"name":"Evangelin","retailers":["value1"],"hub_id":4},
{"id":88,"name":"Louella","retailers":["value4"],"hub_id":4},
{"id":89,"name":"Madge","retailers":["value2"],"hub_id":5},
{"id":90,"name":"Lolita","retailers":["value3"],"hub_id":5},
{"id":91,"name":"Robbin","retailers":["value1"],"hub_id":3},
{"id":92,"name":"Jefferson","retailers":["value1"],"hub_id":5},
{"id":93,"name":"Haydon","retailers":["value3"],"hub_id":3},
{"id":94,"name":"Wendeline","retailers":["value4"],"hub_id":5},
{"id":95,"name":"Sabine","retailers":["value2"],"hub_id":3},
{"id":96,"name":"Chas","retailers":["value4"],"hub_id":3},
{"id":97,"name":"Ariana","retailers":["value4"],"hub_id":3},
{"id":98,"name":"Torin","retailers":["value5"],"hub_id":4},
{"id":99,"name":"Beverlee","retailers":["value5"],"hub_id":3},
{"id":100,"name":"Ned","retailers":["value5"],"hub_id":4}]